LICENSE
MANIFEST.in
README.rst
setup.py
linttest/__init__.py
linttest/base.py
linttest/models.py
linttest/tests.py
linttest.egg-info/PKG-INFO
linttest.egg-info/SOURCES.txt
linttest.egg-info/dependency_links.txt
linttest.egg-info/pbr.json
linttest.egg-info/requires.txt
linttest.egg-info/top_level.txt
linttest/management/__init__.py
linttest/management/commands/__init__.py
linttest/management/commands/linttest.py