Metadata-Version: 1.1
Name: linttest
Version: 0.1.4
Summary: A django lint test runner
Home-page: https://github.com/zapier/django-linttest
Author: Harrison Jackson
Author-email: harrison.jackson@zapier.com
License: UNKNOWN
Download-URL: https://github.com/zapier/django-linttest/tarball/0.1
Platform: UNKNOWN
